{
  "_fv": 24,
  "_type": "achievement",
  "definition": {
    "achievementName": "Bob is back!",
    "achievementDescription": "Bring Bob back to LoloCraftIV",
    "achievementIcon": {
      "value": "Items.EVOKER_SPAWN_EGG"
    },
    "background": "Default",
    "disableDisplay": false,
    "showPopup": true,
    "announceToChat": true,
    "hideIfNotCompleted": true,
    "rewardLoot": [
      "Test"
    ],
    "rewardRecipes": [
      "RedWoodRecipe"
    ],
    "rewardFunction": "No function",
    "rewardXP": 1000,
    "achievementType": "goal",
    "parent": {
      "value": "CUSTOM:Adv02"
    },
    "triggerxml": "<xml xmlns=\"https://developers.google.com/blockly/xml\"><block type=\"block_placed\" x=\"569\" y=\"315\"><value name=\"block\"><block type=\"mcitem_allblocks\"><field name=\"value\">CUSTOM:Bobspawner</field></block></value><next><block type=\"advancement_trigger\" deletable=\"false\"></block></next></block></xml>"
  }
}